itksnap_dls/__init__.py
itksnap_dls/__main__.py
itksnap_dls/segment.py
itksnap_dls/server.py
itksnap_dls/session.py
itksnap_dls-0.0.8.dist-info/licenses/LICENSE.txt
itksnap_dls-0.0.8.dist-info/METADATA
itksnap_dls-0.0.8.dist-info/WHEEL
itksnap_dls-0.0.8.dist-info/top_level.txt
itksnap_dls-0.0.8.dist-info/RECORD
