Metadata-Version: 2.4
Name: itksnap-dls
Version: 0.0.8
Summary: ITK-SNAP interactive deep learning segmentation server
Author-email: Paul Yushkevich <pyushkevich@gmail.com>
Project-URL: Homepage, https://github.com/pyushkevich/itksnap
Classifier: Programming Language :: Python :: 3
Classifier: License :: OSI Approved :: MIT License
Classifier: Operating System :: OS Independent
Classifier: Intended Audience :: Science/Research
Classifier: Development Status :: 4 - Beta
Classifier: Topic :: Scientific/Engineering :: Medical Science Apps.
Requires-Python: >=3.10
License-File: LICENSE.txt
Requires-Dist: fastapi[standard]
Requires-Dist: nnInteractive
Requires-Dist: huggingface_hub
Requires-Dist: ngrok
Dynamic: license-file
